{"is_source_file": false, "format": "", "description": "", "external_files": [], "external_methods": [], "published": [], "classes": [], "methods": [], "calls": [], "search-terms": [], "state": 2, "file_id": 6, "knowledge_revision": 21, "git_revision": "89b398df3fbb92f537ea1325e702aeaf24249c91", "hash": "22f9e17cc1848b56dbb244518ac2707e", "format-version": 4, "code-base-name": "notes_frontend", "filename": "notes_frontend/src/App.css", "revision_history": [{"21": "89b398df3fbb92f537ea1325e702aeaf24249c91"}]}